lib/__init__.py
lib/printer.py
jasonxue_personal_lib-0.0.0.dist-info/METADATA
jasonxue_personal_lib-0.0.0.dist-info/WHEEL
jasonxue_personal_lib-0.0.0.dist-info/top_level.txt
jasonxue_personal_lib-0.0.0.dist-info/RECORD
