Metadata-Version: 2.4
Name: jasonxue_personal_lib
Version: 0.0.0
Summary: jason's python lib
Requires-Python: >=3.6
